AUTHORS
CHANGELOG.txt
DESCRIPTION
LICENSE
MANIFEST.in
README.rst
setup.py
django_user_tags.egg-info/PKG-INFO
django_user_tags.egg-info/SOURCES.txt
django_user_tags.egg-info/dependency_links.txt
django_user_tags.egg-info/top_level.txt
user_tags/__init__.py
user_tags/admin.py
user_tags/forms.py
user_tags/models.py
user_tags/migrations/0001_initial.py
user_tags/migrations/__init__.py
user_tags/south_migrations/0001_initial.py
user_tags/south_migrations/0002_auto.py
user_tags/south_migrations/0003_auto__del_dummymodel__chg_field_usertaggroup_user.py
user_tags/south_migrations/0004_auto__add_unique_usertaggroup_user_name.py
user_tags/south_migrations/__init__.py
user_tags/static/user_tags/css/jquery.tagit.css
user_tags/static/user_tags/js/tag-it.js
user_tags/tests/__init__.py
user_tags/tests/factories.py
user_tags/tests/forms_tests.py
user_tags/tests/jasmine_tests.py
user_tags/tests/models_tests.py
user_tags/tests/settings.py
user_tags/tests/urls.py
user_tags/tests/jasmine_tests/files.json
user_tags/tests/jasmine_tests/spec/do_stuff.spec.js
user_tags/tests/test_app/__init__.py
user_tags/tests/test_app/forms.py
user_tags/tests/test_app/models.py
user_tags/tests/test_app/urls.py
user_tags/tests/test_app/views.py
user_tags/tests/test_app/templates/500.html
user_tags/tests/test_app/templates/test_app/test_view.html
user_tags/tests/test_static/js/jquery-1.7.0.min.js
user_tags/tests/test_static/js/jquery-ui-1.8.16.custom.min.js