Metadata-Version: 1.0
Name: django-user-tags
Version: 1.2.1
Summary: A reusable Django app that enables users of your site to tag items. Each user's
